Workbook

Sheet Autumn 2025
A1: key | B1: Course | C1: Title | D1: Quarter | E1: Year | F1: Day and Time | G1: Instructor | H1: Total Enrollment after Phase 1 | I1: Seats Available after Phase 1 | J1: Phase 1 Price | K1: Total Enrollment after Phase 2 | L1: Seats Available after Phase 2 | M1: Phase 2 Price | N1: Total Enrollment after Phase 1 New Students | O1: Seats Available after Phase 1 New Students | P1: Phase 1 New Students Price | Q1: Total Enrollment after Phase 2 New Students | R1: Seats Available after Phase 2 New Students | S1: Phase 2 New Students Price | T1: Total Enrollment after Phase 3 | U1: Seats Available after Phase 3 | V1: Phase 3 Price
A2: =LEFT('Autumn 2025'!B2,5) -> 42121 | B2: 42121-81 | C2: Merger & Acquisition Strategy | D2: Autumn | E2: 2025 | F2: Wednesday, 6:00 pm - 9:00 pm | G2: Morrissette, Stephen | H2: 70 | I2: CLO | J2: 15000 | K2: 70 | L2: CLO | M2: 15052 | N2: 70 | O2: CLO | P2: 0 | Q2: 70 | R2: CLO | S2: 0 | T2: 70 | U2: CLO | V2: 15040
A3: =LEFT('Autumn 2025'!B3,5) -> 34106 | B3: 34106-01 | C3: Commercializing Innovation: Tools to Research and Analyze Private Enterprises | D3: Autumn | E3: 2025 | F3: Thursday, 01:30 pm - 04:30 pm | G3: Meadow, Scott | H3: 55 | I3: CLO | J3: 9065 | K3: 55 | L3: CLO | M3: 13484 | N3: 55 | O3: CLO | P3: 0 | Q3: 55 | R3: CLO | S3: 0 | T3: 55 | U3: CLO | V3: 0
A4: =LEFT('Autumn 2025'!B4,5) -> 30000 | B4: 30000-01 | C4: Financial Accounting | D4: Autumn | E4: 2025 | F4: Monday, 01:30 pm - 04:30 pm | G4: Nikolaev, Valeri | H4: 3 | I4: 62 | J4: 0 | K4: 4 | L4: 61 | M4: 0 | N4: 65 | O4: CLO | P4: 0 | Q4: 65 | R4: CLO | S4: 777 | T4: 65 | U4: CLO | V4: 1844
A5: =LEFT('Autumn 2025'!B5,5) -> 38120 | B5: 38120-01 | C5: The Study of Behavioral Economics | D5: Autumn | E5: 2025 | F5: Wednesday, 08:30 am - 11:30 am | G5: Dean, Joshua | H5: 70 | I5: CLO | J5: 6012 | K5: 70 | L5: CLO | M5: 12007 | N5: 70 | O5: CLO | P5: 0 | Q5: 70 | R5: CLO | S5: 0 | T5: 70 | U5: CLO | V5: 0
A6: =LEFT('Autumn 2025'!B6,5) -> 30000 | B6: 30000-02 | C6: Financial Accounting | D6: Autumn | E6: 2025 | F6: Tuesday, 08:30 am - 11:30 am | G6: Nikolaev, Valeri | H6: 9 | I6: 56 | J6: 0 | K6: 9 | L6: 56 | M6: 0 | N6: 65 | O6: CLO | P6: 1201 | Q6: 65 | R6: CLO | S6: 0 | T6: 64 | U6: 1 | V6: 0
A7: =LEFT('Autumn 2025'!B7,5) -> 30000 | B7: 30000-03 | C7: Financial Accounting | D7: Autumn | E7: 2025 | F7: Tuesday, 01:30 pm - 04:30 pm | G7: Nikolaev, Valeri | H7: 8 | I7: 57 | J7: 0 | K7: 10 | L7: 55 | M7: 0 | N7: 65 | O7: CLO | P7: 300 | Q7: 65 | R7: CLO | S7: 1243 | T7: 65 | U7: CLO | V7: 2000
A8: =LEFT('Autumn 2025'!B8,5) -> 38103 | B8: 38103-01 | C8: Strategies and Processes of Negotiation | D8: Autumn | E8: 2025 | F8: Wednesday, 01:30 pm - 04:30 pm | G8: Kirgios, Erika | H8: 55 | I8: CLO | J8: 3250 | K8: 55 | L8: CLO | M8: 3000 | N8: 55 | O8: CLO | P8: 0 | Q8: 55 | R8: CLO | S8: 0 | T8: 55 | U8: CLO | V8: 5000
A9: =LEFT('Autumn 2025'!B9,5) -> 30000 | B9: 30000-04 | C9: Financial Accounting | D9: Autumn | E9: 2025 | F9: Friday, 08:30 am - 11:30 am | G9: Granja, Joao | H9: 1 | I9: 64 | J9: 0 | K9: 1 | L9: 64 | M9: 0 | N9: 53 | O9: 12 | P9: 0 | Q9: 54 | R9: 11 | S9: 0 | T9: 52 | U9: 13 | V9: 0
A10: =LEFT('Autumn 2025'!B10,5) -> 30000 | B10: 30000-05 | C10: Financial Accounting | D10: Autumn | E10: 2025 | F10: Friday, 01:30 pm - 04:30 pm | G10: Granja, Joao | H10: 5 | I10: 60 | J10: 0 | K10: 5 | L10: 60 | M10: 0 | N10: 39 | O10: 26 | P10: 0 | Q10: 47 | R10: 18 | S10: 0 | T10: 48 | U10: 17 | V10: 0
A11: =LEFT('Autumn 2025'!B11,5) -> 42001 | B11: 42001-01 | C11: Competitive Strategy | D11: Autumn | E11: 2025 | F11: Thursday, 01:30 pm - 04:30 pm | G11: Wollmann, Thomas | H11: 65 | I11: CLO | J11: 2100 | K11: 65 | L11: CLO | M11: 6035 | N11: 65 | O11: CLO | P11: 0 | Q11: 65 | R11: CLO | S11: 0 | T11: 65 | U11: CLO | V11: 5001
A12: =LEFT('Autumn 2025'!B12,5) -> 30000 | B12: 30000-06 | C12: Financial Accounting | D12: Autumn | E12: 2025 | F12: Wednesday, 08:30 am - 11:30 am | G12: Errico, Marco | H12: 6 | I12: 59 | J12: 0 | K12: 7 | L12: 58 | M12: 0 | N12: 65 | O12: CLO | P12: 88 | Q12: 65 | R12: CLO | S12: 1571 | T12: 65 | U12: CLO | V12: 375
A13: =LEFT('Autumn 2025'!B13,5) -> 42001 | B13: 42001-81 | C13: Competitive Strategy | D13: Autumn | E13: 2025 | F13: Thursday, 6:00 pm - 9:00 pm | G13: Wollmann, Thomas | H13: 65 | I13: CLO | J13: 1598 | K13: 65 | L13: CLO | M13: 4000 | N13: 65 | O13: CLO | P13: 0 | Q13: 65 | R13: CLO | S13: 0 | T13: 65 | U13: CLO | V13: 13505
A14: =LEFT('Autumn 2025'!B14,5) -> 30000 | B14: 30000-07 | C14: Financial Accounting | D14: Autumn | E14: 2025 | F14: Thursday, 08:30 am - 11:30 am | G14: Errico, Marco | H14: 1 | I14: 64 | J14: 0 | K14: 1 | L14: 64 | M14: 0 | N14: 35 | O14: 30 | P14: 0 | Q14: 65 | R14: CLO | S14: 10 | T14: 63 | U14: 2 | V14: 0
A15: =LEFT('Autumn 2025'!B15,5) -> 40101 | B15: 40101-01 | C15: Supply Chain Strategy and Practice | D15: Autumn | E15: 2025 | F15: Monday, 08:30 am - 11:30 am | G15: DeHoratius, Nicole | H15: 65 | I15: CLO | J15: 909 | K15: 65 | L15: CLO | M15: 1988 | N15: 65 | O15: CLO | P15: 0 | Q15: 65 | R15: CLO | S15: 0 | T15: 65 | U15: CLO | V15: 2543
A16: =LEFT('Autumn 2025'!B16,5) -> 30121 | B16: 30121-01 | C16: Accounting for Entrepreneurship: From Start-Up through IPO | D16: Autumn | E16: 2025 | F16: Tuesday, 08:30 am - 11:30 am | G16: Weiss, Ira | H16: 65 | I16: CLO | J16: 500 | K16: 65 | L16: CLO | M16: 4091 | N16: 65 | O16: CLO | P16: 0 | Q16: 65 | R16: CLO | S16: 0 | T16: 65 | U16: CLO | V16: 1500
A17: =LEFT('Autumn 2025'!B17,5) -> 36110 | B17: 36110-81 | C17: Application Development | D17: Autumn | E17: 2025 | F17: Wednesday, 6:00 pm - 9:00 pm | G17: Betina, Raghu | H17: 30 | I17: CLO | J17: 300 | K17: 27 | L17: 3 | M17: 0 | N17: 28 | O17: 2 | P17: 0 | Q17: 29 | R17: 1 | S17: 0 | T17: 30 | U17: CLO | V17: 12000
A18: =LEFT('Autumn 2025'!B18,5) -> 34305 | B18: 34305-01 | C18: Private Equity Transactions | D18: Autumn | E18: 2025 | F18: Thursday, 3:00 pm - 6:00 pm | G18: Ritchie, Stephen | H18: 30 | I18: CLO | J18: 259 | K18: 30 | L18: CLO | M18: 1000 | N18: 30 | O18: CLO | P18: 0 | Q18: 30 | R18: CLO | S18: 0 | T18: 30 | U18: CLO | V18: 0
A19: =LEFT('Autumn 2025'!B19,5) -> 30000 | B19: 30000-81 | C19: Financial Accounting | D19: Autumn | E19: 2025 | F19: Monday, 6:00 pm - 9:00 pm | G19: Nikolaev, Valeri | H19: 12 | I19: 53 | J19: 0 | K19: 12 | L19: 53 | M19: 0 | N19: 30 | O19: 35 | P19: 0 | Q19: 30 | R19: 35 | S19: 0 | T19: 33 | U19: 32 | V19: 0
A20: =LEFT('Autumn 2025'!B20,5) -> 34111 | B20: 34111-01 | C20: Entrepreneurial Selling | D20: Autumn | E20: 2025 | F20: Tuesday, 01:30 pm - 04:30 pm | G20: Alter, Michael | H20: 65 | I20: CLO | J20: 202 | K20: 65 | L20: CLO | M20: 5000 | N20: 65 | O20: CLO | P20: 0 | Q20: 65 | R20: CLO | S20: 0 | T20: 65 | U20: CLO | V20: 6747
A21: =LEFT('Autumn 2025'!B21,5) -> 35222 | B21: 35222-01 | C21: Corporate Governance and Activism - Board and Director Roles in Critical Decisions | D21: Autumn | E21: 2025 | F21: Thursday, 1:30 pm - 4:30 pm | G21: Adrianopoli, Carlin; Hessler, Stephen; Schriesheim, Robert | H21: 60 | I21: CLO | J21: 193 | K21: 60 | L21: CLO | M21: 15000 | N21: 60 | O21: CLO | P21: 0 | Q21: 60 | R21: CLO | S21: 0 | T21: 65 | U21: CLO | V21: 2805
A22: =LEFT('Autumn 2025'!B22,5) -> 30000 | B22: 30000-85 | C22: Financial Accounting | D22: Autumn | E22: 2025 | F22: Saturday, 1:30 pm - 4:30 pm | G22: Errico, Marco | H22: 9 | I22: 56 | J22: 0 | K22: 8 | L22: 57 | M22: 0 | N22: 29 | O22: 36 | P22: 0 | Q22: 28 | R22: 37 | S22: 0 | T22: 36 | U22: 29 | V22: 0
A23: =LEFT('Autumn 2025'!B23,5) -> 30130 | B23: 30130-01 | C23: Financial Statement Analysis | D23: Autumn | E23: 2025 | F23: Wednesday, 01:30 pm - 04:30 pm | G23: Minnis, Michael | H23: 65 | I23: CLO | J23: 3238 | K23: 65 | L23: CLO | M23: 4207 | N23: 65 | O23: CLO | P23: 0 | Q23: 65 | R23: CLO | S23: 0 | T23: 65 | U23: CLO | V23: 3000
A24: =LEFT('Autumn 2025'!B24,5) -> 30130 | B24: 30130-81 | C24: Financial Statement Analysis | D24: Autumn | E24: 2025 | F24: Wednesday, 6:00 pm - 9:00 pm | G24: Minnis, Michael | H24: 25 | I24: 40 | J24: 0 | K24: 24 | L24: 41 | M24: 0 | N24: 29 | O24: 36 | P24: 0 | Q24: 29 | R24: 36 | S24: 0 | T24: 65 | U24: CLO | V24: 1
A25: =LEFT('Autumn 2025'!B25,5) -> 33001 | B25: 33001-01 | C25: Microeconomics | D25: Autumn | E25: 2025 | F25: Monday, 08:30 am - 11:30 am | G25: Hornbeck, Richard | H25: 4 | I25: 61 | J25: 0 | K25: 3 | L25: 62 | M25: 0 | N25: 65 | O25: CLO | P25: 0 | Q25: 65 | R25: CLO | S25: 1031 | T25: 65 | U25: CLO | V25: 0
A26: =LEFT('Autumn 2025'!B26,5) -> 33001 | B26: 33001-02 | C26: Microeconomics | D26: Autumn | E26: 2025 | F26: Monday, 01:30 pm - 04:30 pm | G26: Hornbeck, Richard | H26: 3 | I26: 62 | J26: 0 | K26: 5 | L26: 60 | M26: 0 | N26: 62 | O26: 3 | P26: 0 | Q26: 65 | R26: CLO | S26: 1 | T26: 65 | U26: CLO | V26: 0
A27: =LEFT('Autumn 2025'!B27,5) -> 33001 | B27: 33001-03 | C27: Microeconomics | D27: Autumn | E27: 2025 | F27: Thursday, 08:30 am - 11:30 am | G27: Dizon-Ross, Rebecca | H27: 10 | I27: 55 | J27: 0 | K27: 11 | L27: 54 | M27: 0 | N27: 65 | O27: CLO | P27: 1024 | Q27: 65 | R27: CLO | S27: 3435 | T27: 65 | U27: CLO | V27: 751
A28: =LEFT('Autumn 2025'!B28,5) -> 33001 | B28: 33001-04 | C28: Microeconomics | D28: Autumn | E28: 2025 | F28: Thursday, 01:30 pm - 04:30 pm | G28: Dizon-Ross, Rebecca | H28: 10 | I28: 55 | J28: 0 | K28: 13 | L28: 52 | M28: 0 | N28: 65 | O28: CLO | P28: 1117 | Q28: 65 | R28: CLO | S28: 2137 | T28: 65 | U28: CLO | V28: 0
A29: =LEFT('Autumn 2025'!B29,5) -> 33001 | B29: 33001-05 | C29: Microeconomics | D29: Autumn | E29: 2025 | F29: Friday, 08:30 am - 11:30 am | G29: Dizon-Ross, Rebecca | H29: 2 | I29: 63 | J29: 0 | K29: 2 | L29: 63 | M29: 0 | N29: 62 | O29: 3 | P29: 0 | Q29: 65 | R29: CLO | S29: 0 | T29: 65 | U29: CLO | V29: 0
A30: =LEFT('Autumn 2025'!B30,5) -> 33001 | B30: 33001-06 | C30: Microeconomics | D30: Autumn | E30: 2025 | F30: Tuesday, 01:30 pm - 04:30 pm | G30: Gibbs, Michael | H30: 27 | I30: 38 | J30: 0 | K30: 27 | L30: 38 | M30: 0 | N30: 65 | O30: CLO | P30: 2401 | Q30: 65 | R30: CLO | S30: 2209 | T30: 65 | U30: CLO | V30: 0
A31: =LEFT('Autumn 2025'!B31,5) -> 30116 | B31: 30116-01 | C31: Accounting and Financial Analysis | D31: Autumn | E31: 2025 | F31: Tuesday, 08:30 am - 11:30 am | G31: Christensen, Hans | H31: 5 | I31: 60 | J31: 0 | K31: 6 | L31: 59 | M31: 0 | N31: 65 | O31: CLO | P31: 508 | Q31: 63 | R31: 2 | S31: 0 | T31: 65 | U31: CLO | V31: 10
A32: =LEFT('Autumn 2025'!B32,5) -> 30116 | B32: 30116-02 | C32: Accounting and Financial Analysis | D32: Autumn | E32: 2025 | F32: Tuesday, 01:30 pm - 04:30 pm | G32: Christensen, Hans | H32: 5 | I32: 60 | J32: 0 | K32: 7 | L32: 58 | M32: 0 | N32: 49 | O32: 16 | P32: 0 | Q32: 52 | R32: 13 | S32: 0 | T32: 49 | U32: 16 | V32: 0
A33: =LEFT('Autumn 2025'!B33,5) -> 30118 | B33: 30118-81 | C33: Taxes and Business Strategy | D33: Autumn | E33: 2025 | F33: Monday, 6:00 pm - 9:00 pm | G33: Erickson, Merle | H33: 51 | I33: 14 | J33: 0 | K33: 52 | L33: 13 | M33: 0 | N33: 53 | O33: 12 | P33: 0 | Q33: 53 | R33: 12 | S33: 0 | T33: 65 | U33: CLO | V33: 3000
A34: =LEFT('Autumn 2025'!B34,5) -> 30121 | B34: 30121-02 | C34: Accounting for Entrepreneurship: From Start-Up through IPO | D34: Autumn | E34: 2025 | F34: Monday, 01:30 pm - 04:30 pm | G34: Weiss, Ira | H34: 11 | I34: 54 | J34: 0 | K34: 11 | L34: 54 | M34: 0 | N34: 21 | O34: 44 | P34: 0 | Q34: 21 | R34: 44 | S34: 0 | T34: 41 | U34: 24 | V34: 0
A35: =LEFT('Autumn 2025'!B35,5) -> 30121 | B35: 30121-81 | C35: Accounting for Entrepreneurship: From Start-Up through IPO | D35: Autumn | E35: 2025 | F35: Monday, 6:00 pm - 9:00 pm | G35: Weiss, Ira | H35: 33 | I35: 32 | J35: 0 | K35: 33 | L35: 32 | M35: 0 | N35: 33 | O35: 32 | P35: 0 | Q35: 33 | R35: 32 | S35: 0 | T35: 41 | U35: 24 | V35: 0
A36: =LEFT('Autumn 2025'!B36,5) -> 30121 | B36: 30121-85 | C36: Accounting for Entrepreneurship: From Start-Up through IPO | D36: Autumn | E36: 2025 | F36: Saturday, 1:30 pm - 4:30 pm | G36: Weiss, Ira | H36: 31 | I36: 34 | J36: 0 | K36: 31 | L36: 34 | M36: 0 | N36: 35 | O36: 30 | P36: 0 | Q36: 35 | R36: 30 | S36: 0 | T36: 38 | U36: 27 | V36: 0
A37: =LEFT('Autumn 2025'!B37,5) -> 33001 | B37: 33001-07 | C37: Microeconomics | D37: Autumn | E37: 2025 | F37: Tuesday, 08:30 am - 11:30 am | G37: McClellan, Andrew | H37: 3 | I37: 62 | J37: 0 | K37: 2 | L37: 63 | M37: 0 | N37: 55 | O37: 10 | P37: 0 | Q37: 65 | R37: CLO | S37: 2717 | T37: 65 | U37: CLO | V37: 4023
A38: =LEFT('Autumn 2025'!B38,5) -> 30131 | B38: 30131-01 | C38: Advanced Financial Analysis and Valuation for Global Firms | D38: Autumn | E38: 2025 | F38: Monday, 01:30 pm - 04:30 pm | G38: McClure, Charles | H38: 25 | I38: 40 | J38: 0 | K38: 25 | L38: 40 | M38: 0 | N38: 60 | O38: 5 | P38: 0 | Q38: 62 | R38: 3 | S38: 0 | T38: 62 | U38: 3 | V38: 0
A39: =LEFT('Autumn 2025'!B39,5) -> 30131 | B39: 30131-02 | C39: Advanced Financial Analysis and Valuation for Global Firms | D39: Autumn | E39: 2025 | F39: Monday, 05:00 pm - 08:00 pm | G39: McClure, Charles | H39: 8 | I39: 57 | J39: 0 | K39: 8 | L39: 57 | M39: 0 | N39: 10 | O39: 55 | P39: 0 | Q39: 12 | R39: 53 | S39: 0 | T39: 12 | U39: 53 | V39: 0
A40: =LEFT('Autumn 2025'!B40,5) -> 30131 | B40: 30131-03 | C40: Advanced Financial Analysis and Valuation for Global Firms | D40: Autumn | E40: 2025 | F40: Monday, 08:30 am - 11:30 am | G40: McClure, Charles | H40: 30 | I40: 35 | J40: 0 | K40: 33 | L40: 32 | M40: 0 | N40: 61 | O40: 4 | P40: 0 | Q40: 65 | R40: CLO | S40: 1000 | T40: 65 | U40: CLO | V40: 1
A41: =LEFT('Autumn 2025'!B41,5) -> 30600 | B41: 30600-60 | C41: Workshop in Accounting Research | D41: Autumn | E41: 2025 | F41: Thursday, 01:20 pm - 02:50 pm | G41: Stewart, Christopher; Tomy, Rimmy | H41: 3 | I41: 27 | J41: 0 | K41: 3 | L41: 27 | M41: 0 | N41: 3 | O41: 27 | P41: 0 | Q41: 3 | R41: 27 | S41: 0 | T41: 5 | U41: 25 | V41: 0
A42: =LEFT('Autumn 2025'!B42,5) -> 30900 | B42: 30900-50 | C42: Foundations of Accounting Research | D42: Autumn | E42: 2025 | F42: Tuesday, 08:30 am - 11:30 am | G42: Costello, Anna; Minnis, Michael; Skinner, Douglas | H42: 0 | I42: 20 | J42: 0 | K42: 0 | L42: 20 | M42: 0 | N42: 3 | O42: 17 | P42: 0 | Q42: 3 | R42: 17 | S42: 0 | T42: 3 | U42: 17 | V42: 0
A43: =LEFT('Autumn 2025'!B43,5) -> 30930 | B43: 30930-50 | C43: Research Seminar in Accounting | D43: Autumn | E43: 2025 | F43: Wednesday, 10:00 am - 11:30 am | G43: McClure, Charles; Stewart, Christopher | H43: 0 | I43: 20 | J43: 0 | K43: 0 | L43: 20 | M43: 0 | N43: 0 | O43: 20 | P43: 0 | Q43: 0 | R43: 20 | S43: 0 | T43: 3 | U43: 17 | V43: 0
A44: =LEFT('Autumn 2025'!B44,5) -> 31403 | B44: 31403-01 | C44: Leadership Studio | D44: Autumn | E44: 2025 | F44: Thursday, 01:30 pm - 04:30 pm | G44: Davis, Harry; Tennant, Nancy | H44: 15 | I44: 15 | J44: 0 | K44: 12 | L44: 18 | M44: 0 | N44: 30 | O44: CLO | P44: 10 | Q44: 28 | R44: 2 | S44: 0 | T44: 26 | U44: 4 | V44: 0
A45: =LEFT('Autumn 2025'!B45,5) -> 31403 | B45: 31403-85 | C45: Leadership Studio | D45: Autumn | E45: 2025 | F45: Saturday, 9:00 am - 12:00 pm | G45: Davis, Harry; Tennant, Nancy | H45: 18 | I45: 12 | J45: 0 | K45: 14 | L45: 16 | M45: 0 | N45: 15 | O45: 15 | P45: 0 | Q45: 17 | R45: 13 | S45: 0 | T45: 19 | U45: 11 | V45: 0
A46: =LEFT('Autumn 2025'!B46,5) -> 31425 | B46: 31425-81 | C46: Real Estate and Equity: Leveling the Playing Field | D46: Autumn | E46: 2025 | F46: Wednesday, 6:00 pm - 9:00 pm | G46: Valery, Ernst | H46: 7 | I46: 58 | J46: 0 | K46: 9 | L46: 56 | M46: 0 | N46: 16 | O46: 49 | P46: 0 | Q46: 17 | R46: 48 | S46: 0 | T46: 18 | U46: 47 | V46: 0
A47: =LEFT('Autumn 2025'!B47,5) -> 32120 | B47: 32120-01 | C47: Data Analysis with Python and SQL | D47: Autumn | E47: 2025 | F47: Monday, 08:30 am - 11:30 am | G47: Kattan, Lara | H47: 13 | I47: 22 | J47: 0 | K47: 14 | L47: 21 | M47: 0 | N47: 33 | O47: 2 | P47: 0 | Q47: 34 | R47: 1 | S47: 0 | T47: 35 | U47: CLO | V47: 5000
A48: =LEFT('Autumn 2025'!B48,5) -> 33001 | B48: 33001-81 | C48: Microeconomics | D48: Autumn | E48: 2025 | F48: Monday, 6:00 pm - 9:00 pm | G48: Hornbeck, Richard | H48: 4 | I48: 61 | J48: 0 | K48: 6 | L48: 59 | M48: 0 | N48: 33 | O48: 32 | P48: 0 | Q48: 31 | R48: 34 | S48: 0 | T48: 34 | U48: 31 | V48: 0
A49: =LEFT('Autumn 2025'!B49,5) -> 33001 | B49: 33001-85 | C49: Microeconomics | D49: Autumn | E49: 2025 | F49: Saturday, 9:00 am - 12:00 pm | G49: Gibbs, Michael | H49: 18 | I49: 47 | J49: 0 | K49: 19 | L49: 46 | M49: 0 | N49: 51 | O49: 14 | P49: 0 | Q49: 49 | R49: 16 | S49: 0 | T49: 58 | U49: 7 | V49: 0
A50: =LEFT('Autumn 2025'!B50,5) -> 33002 | B50: 33002-01 | C50: Accelerated Microeconomics | D50: Autumn | E50: 2025 | F50: Tuesday, 01:30 pm - 04:30 pm | G50: Mountjoy, Jack | H50: 13 | I50: 52 | J50: 0 | K50: 12 | L50: 53 | M50: 0 | N50: 70 | O50: CLO | P50: 1000 | Q50: 70 | R50: CLO | S50: 3500 | T50: 70 | U50: CLO | V50: 0
A51: =LEFT('Autumn 2025'!B51,5) -> 33002 | B51: 33002-81 | C51: Accelerated Microeconomics | D51: Autumn | E51: 2025 | F51: Tuesday, 6:00 pm - 9:00 pm | G51: Mountjoy, Jack | H51: 7 | I51: 58 | J51: 0 | K51: 6 | L51: 59 | M51: 0 | N51: 14 | O51: 51 | P51: 0 | Q51: 14 | R51: 51 | S51: 0 | T51: 39 | U51: 26 | V51: 0
A52: =LEFT('Autumn 2025'!B52,5) -> 33401 | B52: 33401-81 | C52: Money and Banking | D52: Autumn | E52: 2025 | F52: Tuesday, 6:00 pm - 9:00 pm | G52: Huber, Kilian | H52: 70 | I52: CLO | J52: 203 | K52: 70 | L52: CLO | M52: 8837 | N52: 70 | O52: CLO | P52: 0 | Q52: 70 | R52: CLO | S52: 0 | T52: 70 | U52: CLO | V52: 15024
A53: =LEFT('Autumn 2025'!B53,5) -> 33401 | B53: 33401-01 | C53: Money and Banking | D53: Autumn | E53: 2025 | F53: Monday, 08:30 am - 11:30 am | G53: Huber, Kilian | H53: 29 | I53: 36 | J53: 0 | K53: 35 | L53: 30 | M53: 0 | N53: 54 | O53: 11 | P53: 0 | Q53: 65 | R53: CLO | S53: 199 | T53: 63 | U53: 2 | V53: 0
A54: =LEFT('Autumn 2025'!B54,5) -> 33401 | B54: 33401-02 | C54: Money and Banking | D54: Autumn | E54: 2025 | F54: Monday, 01:30 pm - 04:30 pm | G54: Huber, Kilian | H54: 53 | I54: 12 | J54: 0 | K54: 57 | L54: 8 | M54: 0 | N54: 64 | O54: 1 | P54: 0 | Q54: 65 | R54: CLO | S54: 1327 | T54: 61 | U54: 4 | V54: 0
A55: =LEFT('Autumn 2025'!B55,5) -> 33401 | B55: 33401-03 | C55: Money and Banking | D55: Autumn | E55: 2025 | F55: Tuesday, 01:30 pm - 04:30 pm | G55: Huber, Kilian | H55: 32 | I55: 33 | J55: 0 | K55: 37 | L55: 28 | M55: 0 | N55: 55 | O55: 10 | P55: 0 | Q55: 58 | R55: 7 | S55: 0 | T55: 65 | U55: CLO | V55: 1000
A56: =LEFT('Autumn 2025'!B56,5) -> 34101 | B56: 34101-02 | C56: Entrepreneurial Finance and Private Equity | D56: Autumn | E56: 2025 | F56: Monday,Wednesday, 01:30 pm - 02:50 pm | G56: Kaplan, Steven | H56: 70 | I56: CLO | J56: 2757 | K56: 70 | L56: CLO | M56: 0 | N56: 70 | O56: CLO | P56: 0 | Q56: 70 | R56: CLO | S56: 0 | T56: 70 | U56: CLO | V56: 0
A57: =LEFT('Autumn 2025'!B57,5) -> 34101 | B57: 34101-01 | C57: Entrepreneurial Finance and Private Equity | D57: Autumn | E57: 2025 | F57: Monday,Wednesday, 10:10 am - 11:30 am | G57: Kaplan, Steven | H57: 70 | I57: CLO | J57: 0 | K57: 70 | L57: CLO | M57: 10000 | N57: 70 | O57: CLO | P57: 0 | Q57: 70 | R57: CLO | S57: 0 | T57: 70 | U57: CLO | V57: 0
A58: =LEFT('Autumn 2025'!B58,5) -> 34102 | B58: 34102-01 | C58: New Venture Strategy | D58: Autumn | E58: 2025 | F58: Wednesday, 01:30 pm - 04:30 pm | G58: Bunch, Gregory | H58: 17 | I58: 48 | J58: 0 | K58: 20 | L58: 45 | M58: 0 | N58: 44 | O58: 21 | P58: 0 | Q58: 54 | R58: 11 | S58: 0 | T58: 47 | U58: 18 | V58: 0
A59: =LEFT('Autumn 2025'!B59,5) -> 33032 | B59: 33032-81 | C59: Managing the Workplace | D59: Autumn | E59: 2025 | F59: Tuesday, 6:00 pm - 9:00 pm | G59: Kole, Stacey | H59: 22 | I59: 43 | J59: 0 | K59: 22 | L59: 43 | M59: 0 | N59: 23 | O59: 42 | P59: 0 | Q59: 23 | R59: 42 | S59: 0 | T59: 43 | U59: 22 | V59: 0
A60: =LEFT('Autumn 2025'!B60,5) -> 33050 | B60: 33050-01 | C60: Macroeconomics and the Business Environment | D60: Autumn | E60: 2025 | F60: Tuesday, 08:30 am - 11:30 am | G60: Vavra, Joseph | H60: 38 | I60: 27 | J60: 0 | K60: 43 | L60: 22 | M60: 0 | N60: 53 | O60: 12 | P60: 0 | Q60: 62 | R60: 3 | S60: 0 | T60: 56 | U60: 9 | V60: 0
A61: =LEFT('Autumn 2025'!B61,5) -> 33050 | B61: 33050-02 | C61: Macroeconomics and the Business Environment | D61: Autumn | E61: 2025 | F61: Wednesday, 08:30 am - 11:30 am | G61: Vavra, Joseph | H61: 23 | I61: 42 | J61: 0 | K61: 27 | L61: 38 | M61: 0 | N61: 46 | O61: 19 | P61: 0 | Q61: 49 | R61: 16 | S61: 0 | T61: 49 | U61: 16 | V61: 0
A62: =LEFT('Autumn 2025'!B62,5) -> 33050 | B62: 33050-81 | C62: Macroeconomics and the Business Environment | D62: Autumn | E62: 2025 | F62: Tuesday, 6:00 pm - 9:00 pm | G62: Vavra, Joseph | H62: 19 | I62: 46 | J62: 0 | K62: 14 | L62: 51 | M62: 0 | N62: 15 | O62: 50 | P62: 0 | Q62: 15 | R62: 50 | S62: 0 | T62: 18 | U62: 47 | V62: 0
A63: =LEFT('Autumn 2025'!B63,5) -> 33230 | B63: 33230-01 | C63: The Economics of Companies | D63: Autumn | E63: 2025 | F63: Tuesday, 08:30 am - 11:30 am | G63: Syverson, Chad | H63: 36 | I63: 29 | J63: 0 | K63: 44 | L63: 21 | M63: 0 | N63: 70 | O63: CLO | P63: 1097 | Q63: 70 | R63: CLO | S63: 0 | T63: 70 | U63: CLO | V63: 2244
A64: =LEFT('Autumn 2025'!B64,5) -> 33230 | B64: 33230-81 | C64: The Economics of Companies | D64: Autumn | E64: 2025 | F64: Tuesday, 6:00 pm - 9:00 pm | G64: Syverson, Chad | H64: 21 | I64: 44 | J64: 0 | K64: 21 | L64: 44 | M64: 0 | N64: 26 | O64: 39 | P64: 0 | Q64: 25 | R64: 40 | S64: 0 | T64: 36 | U64: 29 | V64: 0
A65: =LEFT('Autumn 2025'!B65,5) -> 33351 | B65: 33351-85 | C65: The Business of Pharmaceuticals | D65: Autumn | E65: 2025 | F65: Saturday, 1:30 pm - 4:30 pm | G65: Qato, Ream | H65: 17 | I65: 48 | J65: 0 | K65: 18 | L65: 47 | M65: 0 | N65: 25 | O65: 40 | P65: 0 | Q65: 25 | R65: 40 | S65: 0 | T65: 22 | U65: 43 | V65: 0
A66: =LEFT('Autumn 2025'!B66,5) -> 34102 | B66: 34102-81 | C66: New Venture Strategy | D66: Autumn | E66: 2025 | F66: Tuesday, 6:00 pm - 9:00 pm | G66: Bacon, Jeremie | H66: 22 | I66: 43 | J66: 0 | K66: 16 | L66: 49 | M66: 0 | N66: 26 | O66: 39 | P66: 0 | Q66: 26 | R66: 39 | S66: 0 | T66: 37 | U66: 28 | V66: 0
A67: =LEFT('Autumn 2025'!B67,5) -> 34103 | B67: 34103-01 | C67: Building the New Venture | D67: Autumn | E67: 2025 | F67: Wednesday, 08:30 am - 11:30 am | G67: Metcalf, Scott | H67: 16 | I67: 29 | J67: 0 | K67: 17 | L67: 28 | M67: 0 | N67: 40 | O67: 5 | P67: 0 | Q67: 45 | R67: CLO | S67: 528 | T67: 45 | U67: CLO | V67: 10
A68: =LEFT('Autumn 2025'!B68,5) -> 34901 | B68: 34901-50 | C68: Asset Pricing I | D68: Autumn | E68: 2025 | F68: Monday,Wednesday, 8:30 am - 9:50 am | G68: Hansen, Lars; Nagel, Stefan | H68: 13 | I68: 22 | J68: 0 | K68: 15 | L68: 20 | M68: 0 | N68: 22 | O68: 13 | P68: 0 | Q68: 22 | R68: 13 | S68: 0 | T68: 34 | U68: 1 | V68: 0
A69: =LEFT('Autumn 2025'!B69,5) -> 33610 | B69: 33610-60 | C69: Applied Economics Workshop | D69: Autumn | E69: 2025 | F69: Wednesday, 01:20 pm - 02:50 pm | G69: Minni, Virginia; Zwick, Eric | H69: 3 | I69: 27 | J69: 0 | K69: 5 | L69: 25 | M69: 0 | N69: 8 | O69: 22 | P69: 0 | Q69: 8 | R69: 22 | S69: 0 | T69: 9 | U69: 21 | V69: 0
A70: =LEFT('Autumn 2025'!B70,5) -> 33630 | B70: 33630-60 | C70: Workshop: Money and Banking | D70: Autumn | E70: 2025 | F70: Wednesday, 03:00 pm - 05:30 pm | G70: Patterson, Christina | H70: 0 | I70: 30 | J70: 0 | K70: 0 | L70: 30 | M70: 0 | N70: 0 | O70: 30 | P70: 0 | Q70: 0 | R70: 30 | S70: 0 | T70: 2 | U70: 28 | V70: 0
A71: =LEFT('Autumn 2025'!B71,5) -> 33650 | B71: 33650-60 | C71: Workshop in Macro and International Economics | D71: Autumn | E71: 2025 | F71: Monday, 12:00 pm - 01:15 pm | G71: Adao, Rodrigo | H71: 0 | I71: 30 | J71: 0 | K71: 0 | L71: 30 | M71: 0 | N71: 0 | O71: 30 | P71: 0 | Q71: 0 | R71: 30 | S71: 0 | T71: 2 | U71: 28 | V71: 0
A72: =LEFT('Autumn 2025'!B72,5) -> 33903 | B72: 33903-50 | C72: Microeconomics Reading and Research Seminar | D72: Autumn | E72: 2025 | F72: Monday, 04:30 pm - 06:00 pm | G72: Budish, Eric; Notowidigdo, Matthew | H72: 0 | I72: 22 | J72: 0 | K72: 0 | L72: 22 | M72: 0 | N72: 0 | O72: 22 | P72: 0 | Q72: 0 | R72: 22 | S72: 0 | T72: 2 | U72: 20 | V72: 0
A73: =LEFT('Autumn 2025'!B73,5) -> 33914 | B73: 33914-50 | C73: Topics in Information Economics | D73: Autumn | E73: 2025 | F73: Tuesday, 08:30 am - 11:30 am | G73: Kamenica, Emir | H73: 6 | I73: 29 | J73: 0 | K73: 6 | L73: 29 | M73: 0 | N73: 8 | O73: 27 | P73: 0 | Q73: 8 | R73: 27 | S73: 0 | T73: 13 | U73: 22 | V73: 0
A74: =LEFT('Autumn 2025'!B74,5) -> 33920 | B74: 33920-50 | C74: Health Economics Literature Seminar | D74: Autumn | E74: 2025 | F74: Thursday, 1:30 pm - 3:00 pm | G74: Shapiro, Bradley | H74: 2 | I74: 18 | J74: 0 | K74: 3 | L74: 17 | M74: 0 | N74: 3 | O74: 17 | P74: 0 | Q74: 3 | R74: 17 | S74: 0 | T74: 5 | U74: 15 | V74: 0
A75: =LEFT('Autumn 2025'!B75,5) -> 33921 | B75: 33921-50 | C75: Advanced Industrial Organization I | D75: Autumn | E75: 2025 | F75: Thursday, 08:30 am - 11:30 am | G75: Syverson, Chad | H75: 6 | I75: 29 | J75: 0 | K75: 6 | L75: 29 | M75: 0 | N75: 6 | O75: 29 | P75: 0 | Q75: 6 | R75: 29 | S75: 0 | T75: 13 | U75: 22 | V75: 0
A76: =LEFT('Autumn 2025'!B76,5) -> 33946 | B76: 33946-50 | C76: International Macroeconomics and Trade | D76: Autumn | E76: 2025 | F76: Monday, 8:30 am - 11:30 am | G76: Adao, Rodrigo | H76: 0 | I76: 22 | J76: 0 | K76: 1 | L76: 21 | M76: 0 | N76: 1 | O76: 21 | P76: 0 | Q76: 1 | R76: 21 | S76: 0 | T76: 21 | U76: 4 | V76: 0
A77: =LEFT('Autumn 2025'!B77,5) -> 35000 | B77: 35000-01 | C77: Investments | D77: Autumn | E77: 2025 | F77: Wednesday, 08:30 am - 11:30 am | G77: Vandeweyer, Quentin | H77: 12 | I77: 53 | J77: 0 | K77: 12 | L77: 53 | M77: 0 | N77: 55 | O77: 10 | P77: 0 | Q77: 65 | R77: CLO | S77: 1 | T77: 62 | U77: 3 | V77: 0
A78: =LEFT('Autumn 2025'!B78,5) -> 35000 | B78: 35000-02 | C78: Investments | D78: Autumn | E78: 2025 | F78: Thursday, 08:30 am - 11:30 am | G78: Vandeweyer, Quentin | H78: 13 | I78: 52 | J78: 0 | K78: 14 | L78: 51 | M78: 0 | N78: 29 | O78: 36 | P78: 0 | Q78: 40 | R78: 25 | S78: 0 | T78: 38 | U78: 27 | V78: 0
A79: =LEFT('Autumn 2025'!B79,5) -> 35000 | B79: 35000-03 | C79: Investments | D79: Autumn | E79: 2025 | F79: Tuesday, 08:30 am - 11:30 am | G79: Dew-Becker, Ian | H79: 12 | I79: 53 | J79: 0 | K79: 15 | L79: 50 | M79: 0 | N79: 29 | O79: 36 | P79: 0 | Q79: 35 | R79: 30 | S79: 0 | T79: 35 | U79: 30 | V79: 0
A80: =LEFT('Autumn 2025'!B80,5) -> 35000 | B80: 35000-81 | C80: Investments | D80: Autumn | E80: 2025 | F80: Thursday, 6:00 pm - 9:00 pm | G80: Vandeweyer, Quentin | H80: 37 | I80: 28 | J80: 0 | K80: 37 | L80: 28 | M80: 0 | N80: 39 | O80: 26 | P80: 0 | Q80: 39 | R80: 26 | S80: 0 | T80: 39 | U80: 26 | V80: 0
A81: =LEFT('Autumn 2025'!B81,5) -> 34106 | B81: 34106-81 | C81: Commercializing Innovation: Tools to Research and Analyze Private Enterprises | D81: Autumn | E81: 2025 | F81: Wednesday, 6:00 pm - 9:00 pm | G81: Meadow, Scott | H81: 48 | I81: 7 | J81: 0 | K81: 45 | L81: 10 | M81: 0 | N81: 45 | O81: 10 | P81: 0 | Q81: 45 | R81: 10 | S81: 0 | T81: 55 | U81: CLO | V81: 10001
A82: =LEFT('Autumn 2025'!B82,5) -> 34111 | B82: 34111-85 | C82: Entrepreneurial Selling | D82: Autumn | E82: 2025 | F82: Saturday, 9:00 am - 12:00 pm | G82: Alter, Michael | H82: 42 | I82: 23 | J82: 0 | K82: 39 | L82: 26 | M82: 0 | N82: 42 | O82: 23 | P82: 0 | Q82: 42 | R82: 23 | S82: 0 | T82: 45 | U82: 20 | V82: 0
A83: =LEFT('Autumn 2025'!B83,5) -> 34208 | B83: 34208-01 | C83: Outperform & Outlast: Operating and Investing in Closely Held Businesses | D83: Autumn | E83: 2025 | F83: Monday,Wednesday, 8:30 am - 9:50 am | G83: Shah, Jamie | H83: 26 | I83: 39 | J83: 0 | K83: 23 | L83: 42 | M83: 0 | N83: 39 | O83: 26 | P83: 0 | Q83: 40 | R83: 25 | S83: 0 | T83: 41 | U83: 24 | V83: 0
A84: =LEFT('Autumn 2025'!B84,5) -> 34210 | B84: 34210-01 | C84: Entrepreneurship in Healthcare and Life Sciences | D84: Autumn | E84: 2025 | F84: Monday, 05:00 pm - 08:00 pm | G84: Coe, Brian | H84: 19 | I84: 21 | J84: 0 | K84: 23 | L84: 17 | M84: 0 | N84: 57 | O84: 3 | P84: 0 | Q84: 58 | R84: 4 | S84: 0 | T84: 50 | U84: 12 | V84: 0
A85: =LEFT('Autumn 2025'!B85,5) -> 34220 | B85: 34220-85 | C85: Advanced New Venture Strategy Workshop | D85: Autumn | E85: 2025 | F85: Saturday, 1:30 pm - 4:30 pm | G85: Schrager, James | H85: 21 | I85: 19 | J85: 0 | K85: 24 | L85: 16 | M85: 0 | N85: 26 | O85: 14 | P85: 0 | Q85: 25 | R85: 15 | S85: 0 | T85: 28 | U85: 12 | V85: 0
A86: =LEFT('Autumn 2025'!B86,5) -> 34302 | B86: 34302-01 | C86: Entrepreneurship through Acquisition | D86: Autumn | E86: 2025 | F86: Friday, 01:30 pm - 04:30 pm | G86: Littell, Catherine; Walker, Anthony | H86: 45 | I86: 20 | J86: 0 | K86: 55 | L86: 10 | M86: 0 | N86: 65 | O86: CLO | P86: 2500 | Q86: 65 | R86: CLO | S86: 0 | T86: 63 | U86: 2 | V86: 0
A87: =LEFT('Autumn 2025'!B87,5) -> 34302 | B87: 34302-81 | C87: Entrepreneurship through Acquisition | D87: Autumn | E87: 2025 | F87: Wednesday, 6:00 pm - 9:00 pm | G87: Wolfe, Brian | H87: 60 | I87: 5 | J87: 0 | K87: 60 | L87: 5 | M87: 0 | N87: 64 | O87: 1 | P87: 0 | Q87: 65 | R87: CLO | S87: 2 | T87: 65 | U87: CLO | V87: 1500
A88: =LEFT('Autumn 2025'!B88,5) -> 34705 | B88: 34705-01 | C88: Entrepreneurial Discovery | D88: Autumn | E88: 2025 | F88: Monday, 01:30 pm - 04:30 pm | G88: Tebbe, Mark | H88: 4 | I88: 56 | J88: 0 | K88: 4 | L88: 56 | M88: 0 | N88: 25 | O88: 35 | P88: 0 | Q88: 38 | R88: 22 | S88: 0 | T88: 40 | U88: 20 | V88: 0
A89: =LEFT('Autumn 2025'!B89,5) -> 34705 | B89: 34705-02 | C89: Entrepreneurial Discovery | D89: Autumn | E89: 2025 | F89: Wednesday, 01:30 pm - 04:30 pm | G89: Tebbe, Mark | H89: 14 | I89: 46 | J89: 0 | K89: 18 | L89: 42 | M89: 0 | N89: 60 | O89: CLO | P89: 186 | Q89: 60 | R89: CLO | S89: 500 | T89: 60 | U89: CLO | V89: 2000
A90: =LEFT('Autumn 2025'!B90,5) -> 35141 | B90: 35141-01 | C90: Advanced Models of Security Pricing and Credit Risk | D90: Autumn | E90: 2025 | F90: Thursday, 08:30 am - 11:30 am | G90: Boonstra, Brian | H90: 22 | I90: 43 | J90: 0 | K90: 23 | L90: 42 | M90: 0 | N90: 41 | O90: 24 | P90: 0 | Q90: 41 | R90: 24 | S90: 0 | T90: 41 | U90: 24 | V90: 0
A91: =LEFT('Autumn 2025'!B91,5) -> 34903 | B91: 34903-50 | C91: Corporate Finance I | D91: Autumn | E91: 2025 | F91: Monday, 03:00 pm - 06:00 pm | G91: Diamond, Douglas | H91: 7 | I91: 28 | J91: 0 | K91: 7 | L91: 28 | M91: 0 | N91: 7 | O91: 28 | P91: 0 | Q91: 7 | R91: 28 | S91: 0 | T91: 12 | U91: 23 | V91: 0
A92: =LEFT('Autumn 2025'!B92,5) -> 35200 | B92: 35200-01 | C92: Corporation Finance | D92: Autumn | E92: 2025 | F92: Thursday, 08:30 am - 11:30 am | G92: Vasudevan, Kaushik | H92: 65 | I92: CLO | J92: 1234 | K92: 65 | L92: CLO | M92: 6540 | N92: 65 | O92: CLO | P92: 0 | Q92: 65 | R92: CLO | S92: 0 | T92: 65 | U92: CLO | V92: 4837
A93: =LEFT('Autumn 2025'!B93,5) -> 35200 | B93: 35200-02 | C93: Corporation Finance | D93: Autumn | E93: 2025 | F93: Thursday, 01:30 pm - 04:30 pm | G93: Vasudevan, Kaushik | H93: 38 | I93: 27 | J93: 0 | K93: 48 | L93: 17 | M93: 0 | N93: 52 | O93: 13 | P93: 0 | Q93: 53 | R93: 12 | S93: 0 | T93: 57 | U93: 8 | V93: 0
A94: =LEFT('Autumn 2025'!B94,5) -> 35201 | B94: 35201-01 | C94: Cases in Financial Management | D94: Autumn | E94: 2025 | F94: Wednesday, 08:30 am - 11:30 am | G94: Born, Laura | H94: 65 | I94: CLO | J94: 7103 | K94: 65 | L94: CLO | M94: 14123 | N94: 65 | O94: CLO | P94: 0 | Q94: 65 | R94: CLO | S94: 0 | T94: 65 | U94: CLO | V94: 0
A95: =LEFT('Autumn 2025'!B95,5) -> 35201 | B95: 35201-02 | C95: Cases in Financial Management | D95: Autumn | E95: 2025 | F95: Wednesday, 01:30 pm - 04:30 pm | G95: Born, Laura | H95: 65 | I95: CLO | J95: 5000 | K95: 65 | L95: CLO | M95: 9007 | N95: 65 | O95: CLO | P95: 0 | Q95: 65 | R95: CLO | S95: 0 | T95: 65 | U95: CLO | V95: 0
A96: =LEFT('Autumn 2025'!B96,5) -> 35118 | B96: 35118-01 | C96: Healthcare Finance | D96: Autumn | E96: 2025 | F96: Tuesday, 08:30 am - 11:30 am | G96: Veronesi, Pietro | H96: 28 | I96: 37 | J96: 0 | K96: 31 | L96: 34 | M96: 0 | N96: 31 | O96: 34 | P96: 0 | Q96: 31 | R96: 34 | S96: 0 | T96: 32 | U96: 33 | V96: 0
A97: =LEFT('Autumn 2025'!B97,5) -> 35121 | B97: 35121-01 | C97: Behavioral Finance | D97: Autumn | E97: 2025 | F97: Tuesday, 08:30 am - 11:30 am | G97: Yan, Hongjun | H97: 25 | I97: 40 | J97: 0 | K97: 28 | L97: 37 | M97: 0 | N97: 51 | O97: 14 | P97: 0 | Q97: 50 | R97: 15 | S97: 0 | T97: 46 | U97: 19 | V97: 0
A98: =LEFT('Autumn 2025'!B98,5) -> 35136 | B98: 35136-01 | C98: Blockchains and Decentralized Finance | D98: Autumn | E98: 2025 | F98: Wednesday, 01:30 pm - 04:30 pm | G98: Zhang, Anthony | H98: 15 | I98: 50 | J98: 0 | K98: 21 | L98: 44 | M98: 0 | N98: 26 | O98: 39 | P98: 0 | Q98: 29 | R98: 36 | S98: 0 | T98: 50 | U98: 15 | V98: 0
A99: =LEFT('Autumn 2025'!B99,5) -> 35139 | B99: 35139-01 | C99: The Economics of Digital Asset Products and Markets | D99: Autumn | E99: 2025 | F99: Friday, 01:30 pm - 04:30 pm | G99: van der Merwe, Andria | H99: 47 | I99: 18 | J99: 0 | K99: 54 | L99: 11 | M99: 0 | N99: 70 | O99: CLO | P99: 3676 | Q99: 69 | R99: 1 | S99: 0 | T99: 70 | U99: CLO | V99: 1600
A100: =LEFT('Autumn 2025'!B100,5) -> 37105 | B100: 37105-81 | C100: Data Science for Marketing Decision Making | D100: Autumn | E100: 2025 | F100: Thursday, 6:00 pm - 9:00 pm | G100: Compiani, Giovanni | H100: 12 | I100: 53 | J100: 0 | K100: 12 | L100: 53 | M100: 0 | N100: 12 | O100: 53 | P100: 0 | Q100: 12 | R100: 53 | S100: 0 | T100: 11 | U100: 54 | V100: 0
...
